LICENSE
README.md
pyproject.toml
setup.py
tests/test_correctness.py
torch_fps/__init__.py
torch_fps/binding.cpp
torch_fps/fps.py
torch_fps/fps_cpu.cpp
torch_fps/fps_cuda.cu
torch_fps.egg-info/PKG-INFO
torch_fps.egg-info/SOURCES.txt
torch_fps.egg-info/dependency_links.txt
torch_fps.egg-info/requires.txt
torch_fps.egg-info/top_level.txt