Metadata-Version: 2.4
Name: torch-fps
Version: 0.1.2
Summary: Native PyTorch farthest point sampling for point cloud workloads
Author: Felix Yu
License: MIT License
Classifier: Development Status :: 3 - Alpha
Classifier: Intended Audience :: Science/Research
Classifier: Programming Language :: Python :: 3
Classifier: Programming Language :: Python :: 3 :: Only
Classifier: Programming Language :: Python :: 3.9
Classifier: Programming Language :: Python :: 3.10
Classifier: Programming Language :: Python :: 3.11
Classifier: Programming Language :: Python :: 3.12
Classifier: Topic :: Scientific/Engineering :: Artificial Intelligence
Classifier: Topic :: Scientific/Engineering :: Information Analysis
Requires-Python: >=3.9
License-File: LICENSE
Requires-Dist: torch>=2.1
Dynamic: license-file
